[{"CodigoItem":1,"DataEntrada":"Aug 6, 2021 12:00:00 AM","LocalCompra":"ijdhiashidasd","Tipo":"Camisa","Marca":"avon","Caracteristicas":"ajsdoijaosjdosisa","Tamanho":"Grande","Cor":"Vermelho","ValorPago":70.0,"ValorMargem":140.0,"PrecoSugerido":200.0},{"CodigoItem":2,"DataEntrada":"Sep 9, 2021 12:00:00 AM","LocalCompra":"kjbkajbkedbjaksndfa","Tipo":"Meias","Marca":"hdoasda","Caracteristicas":"aidhiausidhiuasd","Tamanho":"Grande","Cor":"Azul","ValorPago":20.0,"ValorMargem":40.0,"PrecoSugerido":60.0}]